LICENSE-MIT
MANIFEST.in
README.rst
setup.py
hooked/__init__.py
hooked/server.py
hooked.egg-info/PKG-INFO
hooked.egg-info/SOURCES.txt
hooked.egg-info/dependency_links.txt
hooked.egg-info/entry_points.txt
hooked.egg-info/requires.txt
hooked.egg-info/top_level.txt