Metadata-Version: 1.1
Name: hooked
Version: 0.2
Summary: Run command on GitHub and BitBucket POST request hooks
Home-page: https://github.com/bbinet/hooked
Author: Bruno Binet
Author-email: bruno.binet@gmail.com
License: MIT
Keywords: bitbucket,github,hook,post,web,webhook
Platform: UNKNOWN
Classifier: Development Status :: 3 - Alpha
Classifier: Intended Audience :: Developers
Classifier: License :: OSI Approved :: MIT License
Classifier: Operating System :: MacOS :: MacOS X
Classifier: Operating System :: POSIX :: Linux
Classifier: Operating System :: Unix
Classifier: Programming Language :: Python
Classifier: Programming Language :: Python :: 2.6
Classifier: Programming Language :: Python :: 2.7
